{
    "существительное": {
        "Количество уникальных слов": 772,
        "Общее количество слов": 1325
    },
    "союз": {
        "Количество уникальных слов": 17,
        "Общее количество слов": 195
    },
    "прилагательное": {
        "Количество уникальных слов": 344,
        "Общее количество слов": 494
    },
    "частица": {
        "Количество уникальных слов": 9,
        "Общее количество слов": 39
    },
    "глагол": {
        "Количество уникальных слов": 280,
        "Общее количество слов": 345
    },
    "предлог": {
        "Количество уникальных слов": 28,
        "Общее количество слов": 311
    },
    "местоимение-прилагательное": {
        "Количество уникальных слов": 61,
        "Общее количество слов": 112
    },
    "наречие": {
        "Количество уникальных слов": 63,
        "Общее количество слов": 110
    },
    "местоимение-существительное": {
        "Количество уникальных слов": 27,
        "Общее количество слов": 68
    },
    "null": {
        "Количество уникальных слов": 73,
        "Общее количество слов": 111
    },
    "местоименное наречие": {
        "Количество уникальных слов": 5,
        "Общее количество слов": 10
    },
    "числительное": {
        "Количество уникальных слов": 8,
        "Общее количество слов": 11
    },
    "числительное-прилагательное": {
        "Количество уникальных слов": 11,
        "Общее количество слов": 12
    }
}